chat_parser/__init__.py
chat_parser/data_extractor.py
chat_parser/fileparser.py
chat_parser/utils.py
chat_parser/data_extractor/__init__.py
chat_parser/data_extractor/data_extractor.py
chat_parser/data_extractor/fileparser.py
chat_parser/data_extractor/utils.py
chat_parser/telegram/__init__.py
chat_parser/telegram/parser.py
chat_parser/whatsapp/__init__.py
chat_parser/whatsapp/parser.py
chat_parser-0.1.1.dist-info/LICENSE.txt
chat_parser-0.1.1.dist-info/METADATA
chat_parser-0.1.1.dist-info/WHEEL
chat_parser-0.1.1.dist-info/top_level.txt
chat_parser-0.1.1.dist-info/RECORD
