Metadata-Version: 2.1
Name: chat-parser
Version: 0.1.1
Summary: Chat parser for data analytics
Home-page: UNKNOWN
Author: Anggi Kharisma Putra
Author-email: anggikharismaputra@gmail.com
License: MIT
Keywords: chat parser,telegram chat parser,chat data analytic
Platform: UNKNOWN
